lunapy/__init__.py
lunapy/api.py
lunapy/client.py
lunapy/dispatcher.py
lunapy/event.py
lunapy/helper.py
lunapy/router.py
lunapy/type.py
lunapy-0.1.1.dist-info/METADATA
lunapy-0.1.1.dist-info/WHEEL
lunapy-0.1.1.dist-info/top_level.txt
lunapy-0.1.1.dist-info/RECORD
