Metadata-Version: 2.4
Name: lunapy
Version: 0.1.1
Summary: luna python client
Requires-Python: >=3.11
Requires-Dist: aiohttp>=3.12.14
Requires-Dist: websockets>=15.0.1
